[
  {
    "date": "2026-06-30",
    "ticker": "GRAB",
    "price": 3.81,
    "score": 94,
    "days_left": 29,
    "company": "Grab Holdings Limited",
    "pe_target": 4.02,
    "5d_target": 4.86
  },
  {
    "date": "2026-06-30",
    "ticker": "MSFT",
    "price": 371.26,
    "score": 93,
    "days_left": 29,
    "company": "Microsoft Corporation",
    "pe_target": 378.16,
    "5d_target": 405.76
  },
  {
    "date": "2026-06-30",
    "ticker": "ARM",
    "price": 357.5,
    "score": 86,
    "days_left": 29,
    "company": "Arm Holdings plc",
    "pe_target": 382.22,
    "5d_target": 481.1
  },
  {
    "date": "2026-06-30",
    "ticker": "WDC",
    "price": 642.11,
    "score": 84,
    "days_left": 29,
    "company": "Western Digital Corporation",
    "pe_target": 680.45,
    "5d_target": 833.81
  },
  {
    "date": "2026-06-30",
    "ticker": "LRCX",
    "price": 431.65,
    "score": 84,
    "days_left": 29,
    "company": "Lam Research Corporation",
    "pe_target": 455.6,
    "5d_target": 551.4
  }
]