[
  {
    "rank": 1,
    "ticker": "GOOG",
    "company_name": "Alphabet Inc",
    "score": 97,
    "earnings_date": "July 23, 2026",
    "days_left": 31,
    "price": 347.69,
    "pe_target": 358.72,
    "pe_upside": 3.2,
    "3d": 380.78,
    "3d_up": 9.5,
    "5d": 402.84,
    "5d_up": 15.9,
    "analysts": 65,
    "sb": 14,
    "buy": 44,
    "hold": 7,
    "sell": 0,
    "mktcap": 0.0,
    "short_int": 0,
    "iv": 3.2,
    "sector": "Communication Services",
    "sentiment": "Positive",
    "news": {
      "title": "Alphabet shares slide as AI talent exodus rattles investo...",
      "url": "https://finance.yahoo.com/technology/ai/articles/alphabet-shares-slide-ai-talent-181000529.html"
    },
    "price_change_pct": -5.38
  },
  {
    "rank": 2,
    "ticker": "NOW",
    "company_name": "ServiceNow, ",
    "score": 95,
    "earnings_date": "July 22, 2026",
    "days_left": 30,
    "price": 92.56,
    "pe_target": 97.72,
    "pe_upside": 5.6,
    "3d": 108.04,
    "3d_up": 16.7,
    "5d": 118.36,
    "5d_up": 27.9,
    "analysts": 48,
    "sb": 9,
    "buy": 34,
    "hold": 4,
    "sell": 1,
    "mktcap": 0.0,
    "short_int": 5.9,
    "iv": 5.6,
    "sector": "Technology",
    "sentiment": "Positive",
    "news": {
      "title": "Price Prediction: ServiceNow Stock Will Be Worth This Much...",
      "url": "https://finance.yahoo.com/markets/stocks/articles/price-prediction-servicenow-stock-worth-174857426.html"
    },
    "price_change_pct": -2.61
  },
  {
    "rank": 3,
    "ticker": "MU",
    "company_name": "Micron Techn",
    "score": 95,
    "earnings_date": "June 24, 2026",
    "days_left": 2,
    "price": 1191.48,
    "pe_target": 1356.38,
    "pe_upside": 13.8,
    "3d": 1686.15,
    "3d_up": 41.5,
    "5d": 2015.94,
    "5d_up": 69.2,
    "analysts": 44,
    "sb": 9,
    "buy": 30,
    "hold": 4,
    "sell": 1,
    "mktcap": 0.0,
    "short_int": 3.3,
    "iv": 13.8,
    "sector": "Technology",
    "sentiment": "Positive",
    "news": {
      "title": "Tech stocks live: Tech stocks mixed ahead of Micron earnings...",
      "url": "https://finance.yahoo.com/technology/live/tech-stocks-live-tech-stocks-mixed-ahead-of-micron-earnings-wednesday-143422690.html"
    },
    "price_change_pct": 5.07
  },
  {
    "rank": 4,
    "ticker": "CDNS",
    "company_name": "Cadence Desi",
    "score": 86,
    "earnings_date": "July 27, 2026",
    "days_left": 35,
    "price": 382.75,
    "pe_target": 401.64,
    "pe_upside": 4.9,
    "3d": 439.4,
    "3d_up": 14.8,
    "5d": 477.16,
    "5d_up": 24.7,
    "analysts": 24,
    "sb": 5,
    "buy": 16,
    "hold": 2,
    "sell": 1,
    "mktcap": 0.0,
    "short_int": 1.8,
    "iv": 4.9,
    "sector": "Technology",
    "sentiment": "Positive",
    "news": {
      "title": "Is Cadence (CDNS) a Buy as Wall Street Analysts Look O...",
      "url": "https://finance.yahoo.com/markets/stocks/articles/cadence-cdns-buy-wall-street-133005698.html"
    },
    "price_change_pct": -1.2
  },
  {
    "rank": 5,
    "ticker": "GOOGL",
    "company_name": "Alphabet Inc",
    "score": 85,
    "earnings_date": "July 23, 2026",
    "days_left": 31,
    "price": 348.34,
    "pe_target": 350.11,
    "pe_upside": 0.5,
    "3d": 353.65,
    "3d_up": 1.5,
    "5d": 357.19,
    "5d_up": 2.5,
    "analysts": 63,
    "sb": 14,
    "buy": 42,
    "hold": 7,
    "sell": 0,
    "mktcap": 0.0,
    "short_int": 1.4,
    "iv": 0.5,
    "sector": "Communication Services",
    "sentiment": "Positive",
    "news": {
      "title": "Alphabet shares slide as AI talent exodus rattles investo...",
      "url": "https://finance.yahoo.com/technology/ai/articles/alphabet-shares-slide-ai-talent-181000529.html"
    },
    "price_change_pct": -5.35
  },
  {
    "rank": 6,
    "ticker": "ISRG",
    "company_name": "Intuitive Su",
    "score": 84,
    "earnings_date": "July 16, 2026",
    "days_left": 24,
    "price": 402.34,
    "pe_target": 415.55,
    "pe_upside": 3.3,
    "3d": 441.97,
    "3d_up": 9.8,
    "5d": 468.39,
    "5d_up": 16.4,
    "analysts": 33,
    "sb": 6,
    "buy": 16,
    "hold": 9,
    "sell": 2,
    "mktcap": 0.0,
    "short_int": 2.1,
    "iv": 3.3,
    "sector": "Healthcare",
    "sentiment": "Positive",
    "news": {
      "title": "Why Deutsche Bank Still Isn\u2019t Convinced About Intuitive...",
      "url": "https://finance.yahoo.com/markets/stocks/articles/why-deutsche-bank-still-isn-130952082.html"
    },
    "price_change_pct": -1.09
  },
  {
    "rank": 7,
    "ticker": "CLS",
    "company_name": "Celestica In",
    "score": 83,
    "earnings_date": "July 27, 2026",
    "days_left": 35,
    "price": 377.61,
    "pe_target": 411.82,
    "pe_upside": 9.1,
    "3d": 480.24,
    "3d_up": 27.2,
    "5d": 548.66,
    "5d_up": 45.3,
    "analysts": 21,
    "sb": 4,
    "buy": 16,
    "hold": 1,
    "sell": 0,
    "mktcap": 0.0,
    "short_int": 3.1,
    "iv": 9.1,
    "sector": "Technology",
    "sentiment": "Positive",
    "news": {
      "title": "Can CLS' ATS Segment Sustain Margin Growth Despite Revenue...",
      "url": "https://finance.yahoo.com/markets/stocks/articles/cls-ats-segment-sustain-margin-153600752.html"
    },
    "price_change_pct": 1.36
  },
  {
    "rank": 8,
    "ticker": "EFX",
    "company_name": "Equifax Inc.",
    "score": 82,
    "earnings_date": "July 21, 2026",
    "days_left": 29,
    "price": 153.62,
    "pe_target": 168.42,
    "pe_upside": 9.6,
    "3d": 198.02,
    "3d_up": 28.9,
    "5d": 227.62,
    "5d_up": 48.2,
    "analysts": 24,
    "sb": 5,
    "buy": 12,
    "hold": 7,
    "sell": 0,
    "mktcap": 0.0,
    "short_int": 5.7,
    "iv": 9.6,
    "sector": "Industrials",
    "sentiment": "Positive",
    "news": {
      "title": "Equifax (EFX) Stock Valuation Check After Recent Mixed Pe...",
      "url": "https://finance.yahoo.com/markets/stocks/articles/equifax-efx-stock-valuation-check-090908646.html"
    },
    "price_change_pct": -0.2
  },
  {
    "rank": 9,
    "ticker": "NFLX",
    "company_name": "Netflix, Inc",
    "score": 82,
    "earnings_date": "July 16, 2026",
    "days_left": 24,
    "price": 73.31,
    "pe_target": 75.82,
    "pe_upside": 3.4,
    "3d": 80.84,
    "3d_up": 10.3,
    "5d": 85.86,
    "5d_up": 17.1,
    "analysts": 50,
    "sb": 8,
    "buy": 29,
    "hold": 13,
    "sell": 0,
    "mktcap": 0.0,
    "short_int": 2.4,
    "iv": 3.4,
    "sector": "Communication Services",
    "sentiment": "Mixed",
    "news": {
      "title": "Brokers Suggest Investing in Netflix (NFLX): Read This Befor...",
      "url": "https://finance.yahoo.com/markets/stocks/articles/brokers-suggest-investing-netflix-nflx-133004703.html"
    },
    "price_change_pct": -5.26
  },
  {
    "rank": 10,
    "ticker": "TSM",
    "company_name": "Taiwan Semic",
    "score": 81,
    "earnings_date": "July 16, 2026",
    "days_left": 24,
    "price": 467.29,
    "pe_target": 489.14,
    "pe_upside": 4.7,
    "3d": 532.84,
    "3d_up": 14.0,
    "5d": 576.54,
    "5d_up": 23.4,
    "analysts": 19,
    "sb": 5,
    "buy": 12,
    "hold": 2,
    "sell": 0,
    "mktcap": 0.0,
    "short_int": 0.6,
    "iv": 4.7,
    "sector": "Technology",
    "sentiment": "Positive",
    "news": {
      "title": "Why TSMC Doesn\u2019t Even Need to Win the AI Race",
      "url": "https://finance.yahoo.com/technology/ai/articles/why-tsmc-doesn-t-even-193653042.html"
    },
    "price_change_pct": 1.12
  },
  {
    "rank": 11,
    "ticker": "EW",
    "company_name": "Edwards Life",
    "score": 81,
    "earnings_date": "July 23, 2026",
    "days_left": 31,
    "price": 85.96,
    "pe_target": 91.63,
    "pe_upside": 6.6,
    "3d": 102.97,
    "3d_up": 19.8,
    "5d": 114.31,
    "5d_up": 33.0,
    "analysts": 29,
    "sb": 4,
    "buy": 17,
    "hold": 8,
    "sell": 0,
    "mktcap": 0.0,
    "short_int": 2.4,
    "iv": 6.6,
    "sector": "Healthcare",
    "sentiment": "Positive",
    "news": {
      "title": "Edwards Lifesciences Seen Benefiting From CMS Transcathet...",
      "url": "https://finance.yahoo.com/healthcare/articles/edwards-lifesciences-seen-benefiting-cms-154953792.html"
    },
    "price_change_pct": -1.6
  },
  {
    "rank": 12,
    "ticker": "ASML",
    "company_name": "ASML Holding",
    "score": 81,
    "earnings_date": "July 15, 2026",
    "days_left": 23,
    "price": 1892.11,
    "pe_target": 1993.91,
    "pe_upside": 5.4,
    "3d": 2197.51,
    "3d_up": 16.1,
    "5d": 2401.11,
    "5d_up": 26.9,
    "analysts": 44,
    "sb": 6,
    "buy": 32,
    "hold": 4,
    "sell": 2,
    "mktcap": 0.0,
    "short_int": 0.3,
    "iv": 5.4,
    "sector": "Technology",
    "sentiment": "Mixed",
    "news": {
      "title": "Why I'm Not Selling ASML After a 230% Gain",
      "url": "https://finance.yahoo.com/markets/stocks/articles/why-im-not-selling-asml-170420498.html"
    },
    "price_change_pct": -1.95
  },
  {
    "rank": 13,
    "ticker": "RTX",
    "company_name": "RTX Corporat",
    "score": 77,
    "earnings_date": "July 21, 2026",
    "days_left": 29,
    "price": 182.54,
    "pe_target": 187.98,
    "pe_upside": 3.0,
    "3d": 198.86,
    "3d_up": 8.9,
    "5d": 209.74,
    "5d_up": 14.9,
    "analysts": 23,
    "sb": 4,
    "buy": 11,
    "hold": 8,
    "sell": 0,
    "mktcap": 0.0,
    "short_int": 1.2,
    "iv": 3.0,
    "sector": "Industrials",
    "sentiment": "Positive",
    "news": {
      "title": "How Is RTX Advancing Connectivity Across Modern Aviation...",
      "url": "https://finance.yahoo.com/technology/articles/rtx-advancing-connectivity-across-modern-132100646.html"
    },
    "price_change_pct": -1.65
  },
  {
    "rank": 14,
    "ticker": "NOC",
    "company_name": "Northrop Gru",
    "score": 76,
    "earnings_date": "July 21, 2026",
    "days_left": 29,
    "price": 508.53,
    "pe_target": 541.03,
    "pe_upside": 6.4,
    "3d": 606.03,
    "3d_up": 19.2,
    "5d": 671.03,
    "5d_up": 32.0,
    "analysts": 23,
    "sb": 4,
    "buy": 10,
    "hold": 9,
    "sell": 0,
    "mktcap": 0.0,
    "short_int": 1.3,
    "iv": 6.4,
    "sector": "Industrials",
    "sentiment": "Positive",
    "news": {},
    "price_change_pct": -2.49
  },
  {
    "rank": 15,
    "ticker": "LHX",
    "company_name": "L3Harris Tec",
    "score": 76,
    "earnings_date": "July 24, 2026",
    "days_left": 32,
    "price": 285.5,
    "pe_target": 295.67,
    "pe_upside": 3.6,
    "3d": 316.0,
    "3d_up": 10.7,
    "5d": 336.34,
    "5d_up": 17.8,
    "analysts": 21,
    "sb": 3,
    "buy": 13,
    "hold": 5,
    "sell": 0,
    "mktcap": 0.0,
    "short_int": 1.5,
    "iv": 3.6,
    "sector": "Industrials",
    "sentiment": "Positive",
    "news": {
      "title": "With EPS Growth And More, L3Harris Technologies (N...",
      "url": "https://finance.yahoo.com/markets/stocks/articles/eps-growth-more-l3harris-technologies-130006610.html"
    },
    "price_change_pct": -3.16
  },
  {
    "rank": 16,
    "ticker": "ALLY",
    "company_name": "Ally Financi",
    "score": 75,
    "earnings_date": "July 21, 2026",
    "days_left": 29,
    "price": 45.87,
    "pe_target": 48.47,
    "pe_upside": 5.7,
    "3d": 53.67,
    "3d_up": 17.0,
    "5d": 58.87,
    "5d_up": 28.3,
    "analysts": 18,
    "sb": 4,
    "buy": 10,
    "hold": 4,
    "sell": 0,
    "mktcap": 0.0,
    "short_int": 4.0,
    "iv": 5.7,
    "sector": "Financial Services",
    "sentiment": "Positive",
    "news": {
      "title": "Ally Financial Inc. (ALLY): One of the Best Financial Stock...",
      "url": "https://finance.yahoo.com/markets/stocks/articles/ally-financial-inc-ally-one-140757916.html"
    },
    "price_change_pct": 0.84
  },
  {
    "rank": 17,
    "ticker": "HON",
    "company_name": "Honeywell In",
    "score": 75,
    "earnings_date": "July 23, 2026",
    "days_left": 31,
    "price": 229.4,
    "pe_target": 236.25,
    "pe_upside": 3.0,
    "3d": 249.95,
    "3d_up": 9.0,
    "5d": 263.65,
    "5d_up": 14.9,
    "analysts": 27,
    "sb": 3,
    "buy": 12,
    "hold": 10,
    "sell": 2,
    "mktcap": 0.0,
    "short_int": 2.2,
    "iv": 3.0,
    "sector": "Industrials",
    "sentiment": "Positive",
    "news": {
      "title": "What Honeywell\u2019s and DuPont\u2019s Coming Reverse Stock Splits Me...",
      "url": "https://finance.yahoo.com/markets/stocks/articles/honeywell-dupont-coming-reverse-stock-174017468.html"
    },
    "price_change_pct": 0.17
  },
  {
    "rank": 18,
    "ticker": "WST",
    "company_name": "West Pharmac",
    "score": 74,
    "earnings_date": "July 23, 2026",
    "days_left": 31,
    "price": 328.73,
    "pe_target": 353.23,
    "pe_upside": 7.5,
    "3d": 402.23,
    "3d_up": 22.4,
    "5d": 451.23,
    "5d_up": 37.3,
    "analysts": 15,
    "sb": 3,
    "buy": 11,
    "hold": 1,
    "sell": 0,
    "mktcap": 0.0,
    "short_int": 3.8,
    "iv": 7.5,
    "sector": "Healthcare",
    "sentiment": "Positive",
    "news": {
      "title": "West Pharmaceutical Services (WST) Stock Could Be 6.9% U...",
      "url": "https://finance.yahoo.com/markets/stocks/articles/west-pharmaceutical-services-wst-stock-180720496.html"
    },
    "price_change_pct": 0.24
  },
  {
    "rank": 19,
    "ticker": "TXT",
    "company_name": "Textron Inc.",
    "score": 74,
    "earnings_date": "July 23, 2026",
    "days_left": 31,
    "price": 86.42,
    "pe_target": 92.22,
    "pe_upside": 6.7,
    "3d": 103.82,
    "3d_up": 20.1,
    "5d": 115.42,
    "5d_up": 33.6,
    "analysts": 17,
    "sb": 8,
    "buy": 0,
    "hold": 11,
    "sell": 0,
    "mktcap": 0.0,
    "short_int": 3.1,
    "iv": 6.7,
    "sector": "Industrials",
    "sentiment": "Positive",
    "news": {
      "title": "Is Textron Stock Underperforming the S&P 500?",
      "url": "https://finance.yahoo.com/markets/stocks/articles/textron-stock-underperforming-p-500-154912137.html"
    },
    "price_change_pct": -3.41
  },
  {
    "rank": 20,
    "ticker": "SAP",
    "company_name": "SAP SE",
    "score": 72,
    "earnings_date": "July 23, 2026",
    "days_left": 31,
    "price": 149.97,
    "pe_target": 158.43,
    "pe_upside": 5.6,
    "3d": 175.35,
    "3d_up": 16.9,
    "5d": 192.27,
    "5d_up": 28.2,
    "analysts": 16,
    "sb": 3,
    "buy": 10,
    "hold": 3,
    "sell": 0,
    "mktcap": 0.0,
    "short_int": 1.0,
    "iv": 5.6,
    "sector": "Technology",
    "sentiment": "Positive",
    "news": {
      "title": "SAP (XTRA:SAP) Expands Enterprise AI Push With New Partne...",
      "url": "https://finance.yahoo.com/technology/ai/articles/sap-xtra-sap-expands-enterprise-181557901.html"
    },
    "price_change_pct": -3.38
  },
  {
    "rank": 21,
    "ticker": "SNX",
    "company_name": "TD SYNNEX Co",
    "score": 72,
    "earnings_date": "June 25, 2026",
    "days_left": 3,
    "price": 284.53,
    "pe_target": 316.28,
    "pe_upside": 11.2,
    "3d": 379.78,
    "3d_up": 33.5,
    "5d": 443.28,
    "5d_up": 55.8,
    "analysts": 11,
    "sb": 4,
    "buy": 6,
    "hold": 1,
    "sell": 0,
    "mktcap": 0.0,
    "short_int": 2.1,
    "iv": 11.2,
    "sector": "Technology",
    "sentiment": "Positive",
    "news": {
      "title": "TD SYNNEX (SNX) Stock Could Be 22% Undervalued Aft...",
      "url": "https://finance.yahoo.com/markets/stocks/articles/td-synnex-snx-stock-could-071052562.html"
    },
    "price_change_pct": -0.01
  },
  {
    "rank": 22,
    "ticker": "IQV",
    "company_name": "IQVIA Holdin",
    "score": 72,
    "earnings_date": "July 21, 2026",
    "days_left": 29,
    "price": 166.88,
    "pe_target": 182.48,
    "pe_upside": 9.3,
    "3d": 213.68,
    "3d_up": 28.0,
    "5d": 244.88,
    "5d_up": 46.7,
    "analysts": 22,
    "sb": 3,
    "buy": 16,
    "hold": 3,
    "sell": 0,
    "mktcap": 0.0,
    "short_int": 3.4,
    "iv": 9.3,
    "sector": "Healthcare",
    "sentiment": "Mixed",
    "news": {
      "title": "Morgan Stanley favors Charles River Over IQVIA in CRO se...",
      "url": "https://finance.yahoo.com/healthcare/articles/morgan-stanley-favors-charles-river-131321608.html"
    },
    "price_change_pct": -0.53
  },
  {
    "rank": 23,
    "ticker": "GD",
    "company_name": "General Dyna",
    "score": 71,
    "earnings_date": "July 22, 2026",
    "days_left": 30,
    "price": 343.63,
    "pe_target": 352.41,
    "pe_upside": 2.6,
    "3d": 369.97,
    "3d_up": 7.7,
    "5d": 387.53,
    "5d_up": 12.8,
    "analysts": 24,
    "sb": 3,
    "buy": 10,
    "hold": 10,
    "sell": 1,
    "mktcap": 0.0,
    "short_int": 1.1,
    "iv": 2.6,
    "sector": "Industrials",
    "sentiment": "Positive",
    "news": {
      "title": "Jefferies Sees Continued Growth for General Dynamics\u2019 (GD) ...",
      "url": "https://finance.yahoo.com/markets/stocks/articles/jefferies-sees-continued-growth-general-230906025.html"
    },
    "price_change_pct": -1.82
  },
  {
    "rank": 24,
    "ticker": "TXN",
    "company_name": "Texas Instru",
    "score": 71,
    "earnings_date": "July 22, 2026",
    "days_left": 30,
    "price": 329.21,
    "pe_target": 345.9,
    "pe_upside": 5.1,
    "3d": 379.28,
    "3d_up": 15.2,
    "5d": 412.66,
    "5d_up": 25.3,
    "analysts": 36,
    "sb": 2,
    "buy": 15,
    "hold": 17,
    "sell": 2,
    "mktcap": 0.0,
    "short_int": 2.3,
    "iv": 5.1,
    "sector": "Technology",
    "sentiment": "Positive",
    "news": {
      "title": "Texas Instruments (TXN) Launches A Battery Monitor Built F...",
      "url": "https://finance.yahoo.com/technology/articles/texas-instruments-txn-launches-battery-210650341.html"
    },
    "price_change_pct": 1.97
  },
  {
    "rank": 25,
    "ticker": "IBM",
    "company_name": "Internationa",
    "score": 71,
    "earnings_date": "July 22, 2026",
    "days_left": 30,
    "price": 246.99,
    "pe_target": 256.71,
    "pe_upside": 3.9,
    "3d": 276.15,
    "3d_up": 11.8,
    "5d": 295.59,
    "5d_up": 19.7,
    "analysts": 22,
    "sb": 2,
    "buy": 11,
    "hold": 8,
    "sell": 1,
    "mktcap": 0.0,
    "short_int": 3.6,
    "iv": 3.9,
    "sector": "Technology",
    "sentiment": "Positive",
    "news": {
      "title": "How IBM Saved $4.5 Billion Using AI",
      "url": "https://finance.yahoo.com/video/ibm-saved-4-5-billion-155700134.html"
    },
    "price_change_pct": -0.85
  },
  {
    "rank": 26,
    "ticker": "NEE",
    "company_name": "NextEra Ener",
    "score": 70,
    "earnings_date": "July 22, 2026",
    "days_left": 30,
    "price": 86.83,
    "pe_target": 88.78,
    "pe_upside": 2.2,
    "3d": 92.68,
    "3d_up": 6.7,
    "5d": 96.58,
    "5d_up": 11.2,
    "analysts": 22,
    "sb": 3,
    "buy": 11,
    "hold": 7,
    "sell": 1,
    "mktcap": 0.0,
    "short_int": 0.0,
    "iv": 2.2,
    "sector": "Utilities",
    "sentiment": "Positive",
    "news": {
      "title": "NEE and SO: Which Utility Stock Is Better Positioned for ...",
      "url": "https://finance.yahoo.com/markets/stocks/articles/nee-utility-stock-better-positioned-163800800.html"
    },
    "price_change_pct": 0.09
  },
  {
    "rank": 27,
    "ticker": "FLEX",
    "company_name": "Flex Ltd.",
    "score": 70,
    "earnings_date": "July 22, 2026",
    "days_left": 30,
    "price": 151.87,
    "pe_target": 174.66,
    "pe_upside": 15.0,
    "3d": 220.24,
    "3d_up": 45.0,
    "5d": 265.82,
    "5d_up": 75.0,
    "analysts": 11,
    "sb": 3,
    "buy": 7,
    "hold": 1,
    "sell": 0,
    "mktcap": 0.0,
    "short_int": 2.1,
    "iv": 15.0,
    "sector": "Technology",
    "sentiment": "Positive",
    "news": {
      "title": "Flex Ltd. (FLEX) to Join S&P 500 Index on June 22...",
      "url": "https://finance.yahoo.com/markets/stocks/articles/flex-ltd-flex-join-p-092215885.html"
    },
    "price_change_pct": 2.89
  },
  {
    "rank": 28,
    "ticker": "PENN",
    "company_name": "PENN Enterta",
    "score": 68,
    "earnings_date": "July 23, 2026",
    "days_left": 31,
    "price": 21.04,
    "pe_target": 23.0,
    "pe_upside": 9.3,
    "3d": 26.92,
    "3d_up": 27.9,
    "5d": 30.84,
    "5d_up": 46.6,
    "analysts": 20,
    "sb": 3,
    "buy": 7,
    "hold": 9,
    "sell": 1,
    "mktcap": 0.0,
    "short_int": 17.2,
    "iv": 9.3,
    "sector": "Consumer Cyclical",
    "sentiment": "Positive",
    "news": {
      "title": "Is PENN Entertainment, Inc. (PENN) A Good Stock To Buy No...",
      "url": "https://finance.yahoo.com/markets/stocks/articles/penn-entertainment-inc-penn-good-194020870.html"
    },
    "price_change_pct": -1.22
  },
  {
    "rank": 29,
    "ticker": "TEL",
    "company_name": "TE Connectiv",
    "score": 68,
    "earnings_date": "July 22, 2026",
    "days_left": 30,
    "price": 213.87,
    "pe_target": 230.72,
    "pe_upside": 7.9,
    "3d": 264.42,
    "3d_up": 23.6,
    "5d": 298.12,
    "5d_up": 39.4,
    "analysts": 19,
    "sb": 1,
    "buy": 12,
    "hold": 6,
    "sell": 0,
    "mktcap": 0.0,
    "short_int": 2.9,
    "iv": 7.9,
    "sector": "Technology",
    "sentiment": "Positive",
    "news": {
      "title": "TE Connectivity (TEL) Is Down 5.9% After AI Data Center Rev...",
      "url": "https://finance.yahoo.com/markets/stocks/articles/te-connectivity-tel-down-5-031340987.html"
    },
    "price_change_pct": -1.73
  },
  {
    "rank": 30,
    "ticker": "NOK",
    "company_name": "Nokia Oyj",
    "score": 67,
    "earnings_date": "July 23, 2026",
    "days_left": 31,
    "price": 14.54,
    "pe_target": 15.68,
    "pe_upside": 7.9,
    "3d": 17.98,
    "3d_up": 23.7,
    "5d": 20.28,
    "5d_up": 39.6,
    "analysts": 11,
    "sb": 4,
    "buy": 4,
    "hold": 2,
    "sell": 1,
    "mktcap": 0.0,
    "short_int": 1.2,
    "iv": 7.9,
    "sector": "Technology",
    "sentiment": "Positive",
    "news": {
      "title": "Nokia (HLSE:NOKIA) Stock Price Looks Full After 173% Year...",
      "url": "https://finance.yahoo.com/markets/stocks/articles/nokia-hlse-nokia-stock-price-151156736.html"
    },
    "price_change_pct": 7.71
  },
  {
    "rank": 31,
    "ticker": "INTC",
    "company_name": "Intel Corpor",
    "score": 66,
    "earnings_date": "July 23, 2026",
    "days_left": 31,
    "price": 140.13,
    "pe_target": 153.32,
    "pe_upside": 9.4,
    "3d": 179.7,
    "3d_up": 28.2,
    "5d": 206.08,
    "5d_up": 47.1,
    "analysts": 48,
    "sb": 2,
    "buy": 11,
    "hold": 31,
    "sell": 4,
    "mktcap": 0.0,
    "short_int": 2.7,
    "iv": 9.4,
    "sector": "Technology",
    "sentiment": "Positive",
    "news": {
      "title": "Nvidia Stock Is Falling on a Good Day for Intel and Other...",
      "url": "https://www.barrons.com/articles/nvidia-stock-price-amd-intel-aed87973?siteid=yhoof2&yptr=yahoo"
    },
    "price_change_pct": 4.58
  },
  {
    "rank": 32,
    "ticker": "SHW",
    "company_name": "The Sherwin-",
    "score": 66,
    "earnings_date": "July 21, 2026",
    "days_left": 29,
    "price": 318.42,
    "pe_target": 337.53,
    "pe_upside": 6.0,
    "3d": 375.75,
    "3d_up": 18.0,
    "5d": 413.97,
    "5d_up": 30.0,
    "analysts": 24,
    "sb": 3,
    "buy": 10,
    "hold": 11,
    "sell": 0,
    "mktcap": 0.0,
    "short_int": 2.6,
    "iv": 6.0,
    "sector": "Basic Materials",
    "sentiment": "Mixed",
    "news": {
      "title": "Why Citi Sees a Potential Upside Opportunity in Sherwin-Will...",
      "url": "https://finance.yahoo.com/markets/stocks/articles/why-citi-sees-potential-upside-125007503.html"
    },
    "price_change_pct": -0.74
  },
  {
    "rank": 33,
    "ticker": "WAL",
    "company_name": "Western Alli",
    "score": 63,
    "earnings_date": "July 16, 2026",
    "days_left": 24,
    "price": 79.12,
    "pe_target": 85.86,
    "pe_upside": 8.5,
    "3d": 99.34,
    "3d_up": 25.6,
    "5d": 112.82,
    "5d_up": 42.6,
    "analysts": 15,
    "sb": 4,
    "buy": 7,
    "hold": 4,
    "sell": 0,
    "mktcap": 0.0,
    "short_int": 0.1,
    "iv": 8.5,
    "sector": "Financial Services",
    "sentiment": "Mixed",
    "news": {
      "title": "Q1 Earnings Highlights: Western Alliance Bancorporation ...",
      "url": "https://finance.yahoo.com/markets/stocks/articles/q1-earnings-highlights-western-alliance-204128870.html"
    },
    "price_change_pct": -0.99
  },
  {
    "rank": 34,
    "ticker": "VICR",
    "company_name": "Vicor Corpor",
    "score": 63,
    "earnings_date": "July 21, 2026",
    "days_left": 29,
    "price": 367.8,
    "pe_target": 456.0,
    "pe_upside": 24.0,
    "3d": 632.4,
    "3d_up": 71.9,
    "5d": 808.8,
    "5d_up": 119.9,
    "analysts": 4,
    "sb": 2,
    "buy": 2,
    "hold": 0,
    "sell": 0,
    "mktcap": 0.0,
    "short_int": 7.6,
    "iv": 24.0,
    "sector": "Technology",
    "sentiment": "Positive",
    "news": {
      "title": "Vicor\u2019s Record Quarter And Guidance Test Market Nerves A...",
      "url": "https://finance.yahoo.com/markets/stocks/articles/vicor-record-quarter-guidance-test-081205307.html"
    },
    "price_change_pct": 11.06
  },
  {
    "rank": 35,
    "ticker": "TDY",
    "company_name": "Teledyne Tec",
    "score": 60,
    "earnings_date": "July 22, 2026",
    "days_left": 30,
    "price": 614.79,
    "pe_target": 659.78,
    "pe_upside": 7.3,
    "3d": 749.76,
    "3d_up": 22.0,
    "5d": 839.74,
    "5d_up": 36.6,
    "analysts": 13,
    "sb": 3,
    "buy": 7,
    "hold": 3,
    "sell": 0,
    "mktcap": 0.0,
    "short_int": 3.9,
    "iv": 7.3,
    "sector": "Technology",
    "sentiment": "Mixed",
    "news": {
      "title": "Teledyne Technologies (TDY) Stock Could Be 15.9% Below Fai...",
      "url": "https://finance.yahoo.com/markets/stocks/articles/teledyne-technologies-tdy-stock-could-020742224.html"
    },
    "price_change_pct": -0.77
  },
  {
    "rank": 36,
    "ticker": "FISV",
    "company_name": "Fiserv, Inc.",
    "score": 60,
    "earnings_date": "July 22, 2026",
    "days_left": 30,
    "price": 47.55,
    "pe_target": 49.5,
    "pe_upside": 4.1,
    "3d": 53.4,
    "3d_up": 12.3,
    "5d": 57.3,
    "5d_up": 20.5,
    "analysts": 34,
    "sb": 3,
    "buy": 6,
    "hold": 23,
    "sell": 2,
    "mktcap": 0.0,
    "short_int": 0,
    "iv": 4.1,
    "sector": "Technology",
    "sentiment": "Mixed",
    "news": {
      "title": "Why Fiserv (FISV) Stock Is Up Today",
      "url": "https://finance.yahoo.com/markets/stocks/articles/why-fiserv-fisv-stock-today-181251520.html"
    },
    "price_change_pct": -0.65
  },
  {
    "rank": 37,
    "ticker": "RMBS",
    "company_name": "Rambus Inc.",
    "score": 59,
    "earnings_date": "July 27, 2026",
    "days_left": 35,
    "price": 137.78,
    "pe_target": 166.84,
    "pe_upside": 21.1,
    "3d": 224.96,
    "3d_up": 63.3,
    "5d": 283.08,
    "5d_up": 105.5,
    "analysts": 8,
    "sb": 5,
    "buy": 2,
    "hold": 2,
    "sell": 0,
    "mktcap": 0.0,
    "short_int": 9.1,
    "iv": 21.1,
    "sector": "Technology",
    "sentiment": "Mixed",
    "news": {
      "title": "Rambus Is Poised for a Pullback Despite Rising 42% YTD...",
      "url": "https://finance.yahoo.com/markets/stocks/articles/rambus-poised-pullback-despite-rising-163710897.html"
    },
    "price_change_pct": -2.4
  },
  {
    "rank": 38,
    "ticker": "MXL",
    "company_name": "MaxLinear, I",
    "score": 59,
    "earnings_date": "July 22, 2026",
    "days_left": 30,
    "price": 97.39,
    "pe_target": 118.89,
    "pe_upside": 22.1,
    "3d": 161.89,
    "3d_up": 66.2,
    "5d": 204.89,
    "5d_up": 110.4,
    "analysts": 11,
    "sb": 1,
    "buy": 6,
    "hold": 4,
    "sell": 0,
    "mktcap": 0.0,
    "short_int": 4.5,
    "iv": 22.1,
    "sector": "Technology",
    "sentiment": "Positive",
    "news": {
      "title": "MXL vs. QCOM: Which Wireless Connectivity Chip Stock Wins...",
      "url": "https://finance.yahoo.com/markets/stocks/articles/mxl-vs-qcom-wireless-connectivity-120800753.html"
    },
    "price_change_pct": 9.72
  },
  {
    "rank": 39,
    "ticker": "TSLA",
    "company_name": "Tesla, Inc.",
    "score": 58,
    "earnings_date": "July 22, 2026",
    "days_left": 30,
    "price": 407.51,
    "pe_target": 410.25,
    "pe_upside": 0.7,
    "3d": 415.73,
    "3d_up": 2.0,
    "5d": 421.21,
    "5d_up": 3.4,
    "analysts": 47,
    "sb": 5,
    "buy": 18,
    "hold": 18,
    "sell": 6,
    "mktcap": 0.0,
    "short_int": 2.3,
    "iv": 0.7,
    "sector": "Consumer Cyclical",
    "sentiment": "Mixed",
    "news": {},
    "price_change_pct": 1.75
  },
  {
    "rank": 40,
    "ticker": "AVY",
    "company_name": "Avery Dennis",
    "score": 57,
    "earnings_date": "July 21, 2026",
    "days_left": 29,
    "price": 157.49,
    "pe_target": 172.71,
    "pe_upside": 9.7,
    "3d": 203.15,
    "3d_up": 29.0,
    "5d": 233.59,
    "5d_up": 48.3,
    "analysts": 11,
    "sb": 2,
    "buy": 7,
    "hold": 2,
    "sell": 0,
    "mktcap": 0.0,
    "short_int": 3.3,
    "iv": 9.7,
    "sector": "Consumer Cyclical",
    "sentiment": "Mixed",
    "news": {
      "title": "Is Avery Dennison Stock Underperforming the Dow?...",
      "url": "https://finance.yahoo.com/markets/stocks/articles/avery-dennison-stock-underperforming-dow-095903283.html"
    },
    "price_change_pct": -0.75
  },
  {
    "rank": 41,
    "ticker": "ROP",
    "company_name": "Roper Techno",
    "score": 57,
    "earnings_date": "July 21, 2026",
    "days_left": 29,
    "price": 325.69,
    "pe_target": 349.56,
    "pe_upside": 7.3,
    "3d": 397.32,
    "3d_up": 22.0,
    "5d": 445.08,
    "5d_up": 36.7,
    "analysts": 20,
    "sb": 2,
    "buy": 7,
    "hold": 8,
    "sell": 3,
    "mktcap": 0.0,
    "short_int": 4.8,
    "iv": 7.3,
    "sector": "Technology",
    "sentiment": "Mixed",
    "news": {
      "title": "Wall Street Analysts Believe Roper Technologies (R...",
      "url": "https://finance.yahoo.com/markets/stocks/articles/wall-street-analysts-believe-roper-135503361.html"
    },
    "price_change_pct": -1.38
  },
  {
    "rank": 42,
    "ticker": "PRGS",
    "company_name": "Progress Sof",
    "score": 57,
    "earnings_date": "June 30, 2026",
    "days_left": 8,
    "price": 27.42,
    "pe_target": 34.74,
    "pe_upside": 26.7,
    "3d": 49.38,
    "3d_up": 80.1,
    "5d": 64.02,
    "5d_up": 133.5,
    "analysts": 6,
    "sb": 0,
    "buy": 5,
    "hold": 1,
    "sell": 0,
    "mktcap": 0.0,
    "short_int": 14.5,
    "iv": 26.7,
    "sector": "Technology",
    "sentiment": "Positive",
    "news": {
      "title": "A Look At Progress Software (PRGS) Valuation After Recent Sh...",
      "url": "https://finance.yahoo.com/markets/stocks/articles/look-progress-software-prgs-valuation-080805096.html"
    },
    "price_change_pct": -7.61
  },
  {
    "rank": 43,
    "ticker": "AMKR",
    "company_name": "Amkor Techno",
    "score": 56,
    "earnings_date": "July 27, 2026",
    "days_left": 35,
    "price": 92.24,
    "pe_target": 111.08,
    "pe_upside": 20.4,
    "3d": 148.76,
    "3d_up": 61.3,
    "5d": 186.44,
    "5d_up": 102.1,
    "analysts": 10,
    "sb": 2,
    "buy": 3,
    "hold": 5,
    "sell": 0,
    "mktcap": 0.0,
    "short_int": 13.7,
    "iv": 20.4,
    "sector": "Technology",
    "sentiment": "Positive",
    "news": {
      "title": "Amkor Technology, Inc. (AMKR) Is a Trending Stock: Facts to...",
      "url": "https://finance.yahoo.com/markets/stocks/articles/amkor-technology-inc-amkr-trending-130005003.html"
    },
    "price_change_pct": 1.97
  },
  {
    "rank": 44,
    "ticker": "SSNC",
    "company_name": "SS&C Technol",
    "score": 56,
    "earnings_date": "July 22, 2026",
    "days_left": 30,
    "price": 64.95,
    "pe_target": 69.27,
    "pe_upside": 6.7,
    "3d": 77.91,
    "3d_up": 20.0,
    "5d": 86.55,
    "5d_up": 33.3,
    "analysts": 9,
    "sb": 3,
    "buy": 4,
    "hold": 2,
    "sell": 0,
    "mktcap": 0.0,
    "short_int": 3.2,
    "iv": 6.7,
    "sector": "Technology",
    "sentiment": "Mixed",
    "news": {
      "title": "A Look Back at Data & Business Process Services Stocks...",
      "url": "https://finance.yahoo.com/markets/stocks/articles/look-back-data-business-process-190150790.html"
    },
    "price_change_pct": -0.72
  },
  {
    "rank": 45,
    "ticker": "OMC",
    "company_name": "Omnicom Grou",
    "score": 56,
    "earnings_date": "July 21, 2026",
    "days_left": 29,
    "price": 71.88,
    "pe_target": 77.14,
    "pe_upside": 7.3,
    "3d": 87.68,
    "3d_up": 22.0,
    "5d": 98.22,
    "5d_up": 36.7,
    "analysts": 13,
    "sb": 3,
    "buy": 5,
    "hold": 4,
    "sell": 1,
    "mktcap": 0.0,
    "short_int": 11.3,
    "iv": 7.3,
    "sector": "Communication Services",
    "sentiment": "Mixed",
    "news": {
      "title": "Goldman Sachs Sees Advertising Sector Recovery Benefi...",
      "url": "https://finance.yahoo.com/media-advertising/articles/goldman-sachs-sees-advertising-sector-232255549.html"
    },
    "price_change_pct": 0.74
  },
  {
    "rank": 46,
    "ticker": "CBRS",
    "company_name": "Cerebras Sys",
    "score": 56,
    "earnings_date": "June 23, 2026",
    "days_left": 1,
    "price": 231.97,
    "pe_target": 269.62,
    "pe_upside": 16.2,
    "3d": 344.92,
    "3d_up": 48.7,
    "5d": 420.22,
    "5d_up": 81.2,
    "analysts": 10,
    "sb": 3,
    "buy": 7,
    "hold": 0,
    "sell": 0,
    "mktcap": 0.0,
    "short_int": 17.1,
    "iv": 16.2,
    "sector": "Technology",
    "sentiment": "",
    "news": {
      "title": "Cerebras Stock Gets Major Vote of Confidence as Key Earnings...",
      "url": "https://finance.yahoo.com/technology/ai/articles/cerebras-stock-gets-major-vote-170824831.html"
    },
    "price_change_pct": -1.17
  },
  {
    "rank": 47,
    "ticker": "STM",
    "company_name": "STMicroelect",
    "score": 56,
    "earnings_date": "July 23, 2026",
    "days_left": 31,
    "price": 79.95,
    "pe_target": 86.3,
    "pe_upside": 7.9,
    "3d": 99.0,
    "3d_up": 23.8,
    "5d": 111.7,
    "5d_up": 39.7,
    "analysts": 14,
    "sb": 7,
    "buy": 0,
    "hold": 7,
    "sell": 0,
    "mktcap": 0.0,
    "short_int": 2.0,
    "iv": 7.9,
    "sector": "Technology",
    "sentiment": "Negative",
    "news": {
      "title": "STMicroelectronics (ENXTPA:STMPA) Stock Could Be 46.3% ...",
      "url": "https://finance.yahoo.com/markets/stocks/articles/stmicroelectronics-enxtpa-stmpa-stock-could-100908889.html"
    },
    "price_change_pct": 1.99
  },
  {
    "rank": 48,
    "ticker": "PCAR",
    "company_name": "PACCAR Inc",
    "score": 51,
    "earnings_date": "July 21, 2026",
    "days_left": 29,
    "price": 119.81,
    "pe_target": 127.21,
    "pe_upside": 6.2,
    "3d": 142.01,
    "3d_up": 18.5,
    "5d": 156.81,
    "5d_up": 30.9,
    "analysts": 19,
    "sb": 1,
    "buy": 5,
    "hold": 13,
    "sell": 0,
    "mktcap": 0.0,
    "short_int": 3.1,
    "iv": 6.2,
    "sector": "Industrials",
    "sentiment": "Mixed",
    "news": {
      "title": "PACCAR (PCAR) Gains from \u201cHALO Trade\u201d",
      "url": "https://finance.yahoo.com/markets/stocks/articles/paccar-pcar-gains-halo-trade-132419417.html"
    },
    "price_change_pct": 0.72
  },
  {
    "rank": 49,
    "ticker": "INFY",
    "company_name": "Infosys Limi",
    "score": 50,
    "earnings_date": "July 23, 2026",
    "days_left": 31,
    "price": 10.63,
    "pe_target": 11.52,
    "pe_upside": 8.3,
    "3d": 13.27,
    "3d_up": 24.8,
    "5d": 15.04,
    "5d_up": 41.4,
    "analysts": 12,
    "sb": 3,
    "buy": 2,
    "hold": 7,
    "sell": 0,
    "mktcap": 0.0,
    "short_int": 4.1,
    "iv": 8.3,
    "sector": "Technology",
    "sentiment": "Mixed",
    "news": {
      "title": "Infosys (INFY) Partners With Valmet On Enterprise-Wide...",
      "url": "https://finance.yahoo.com/technology/articles/infosys-infy-partners-valmet-enterprise-190353544.html"
    },
    "price_change_pct": 0.57
  },
  {
    "rank": 50,
    "ticker": "SCCO",
    "company_name": "Southern Cop",
    "score": 50,
    "earnings_date": "July 27, 2026",
    "days_left": 35,
    "price": 191.36,
    "pe_target": 202.38,
    "pe_upside": 5.8,
    "3d": 224.42,
    "3d_up": 17.3,
    "5d": 246.46,
    "5d_up": 28.8,
    "analysts": 17,
    "sb": 0,
    "buy": 2,
    "hold": 5,
    "sell": 10,
    "mktcap": 0.0,
    "short_int": 12.1,
    "iv": 5.8,
    "sector": "Basic Materials",
    "sentiment": "Positive",
    "news": {
      "title": "Here's How Much You'd Have If You Invested $1000 in Southe...",
      "url": "https://finance.yahoo.com/markets/stocks/articles/heres-much-youd-invested-1000-123004953.html"
    },
    "price_change_pct": -0.81
  },
  {
    "rank": 51,
    "ticker": "WSE",
    "company_name": "Wise Group p",
    "score": 48,
    "earnings_date": "June 25, 2026",
    "days_left": 3,
    "price": 10.91,
    "pe_target": 11.26,
    "pe_upside": 3.2,
    "3d": 11.96,
    "3d_up": 9.6,
    "5d": 12.66,
    "5d_up": 16.0,
    "analysts": 6,
    "sb": 1,
    "buy": 5,
    "hold": 0,
    "sell": 0,
    "mktcap": 0.0,
    "short_int": 0,
    "iv": 3.2,
    "sector": "Technology",
    "sentiment": "",
    "news": {
      "title": "Wise Group (WSE): 10 Best Young Stocks with the Highest Ups...",
      "url": "https://finance.yahoo.com/markets/stocks/articles/wise-group-wse-10-best-183824834.html"
    },
    "price_change_pct": 0.65
  },
  {
    "rank": 52,
    "ticker": "LMT",
    "company_name": "Lockheed Mar",
    "score": 47,
    "earnings_date": "July 21, 2026",
    "days_left": 29,
    "price": 493.86,
    "pe_target": 508.46,
    "pe_upside": 3.0,
    "3d": 537.66,
    "3d_up": 8.9,
    "5d": 566.86,
    "5d_up": 14.8,
    "analysts": 21,
    "sb": 2,
    "buy": 4,
    "hold": 14,
    "sell": 1,
    "mktcap": 0.0,
    "short_int": 1.4,
    "iv": 3.0,
    "sector": "Industrials",
    "sentiment": "Negative",
    "news": {
      "title": "Defense Stock Showdown: SpaceX vs. Lockheed Martin -- Which...",
      "url": "https://finance.yahoo.com/markets/stocks/articles/defense-stock-showdown-spacex-vs-072500656.html"
    },
    "price_change_pct": -3.34
  },
  {
    "rank": 53,
    "ticker": "FAST",
    "company_name": "Fastenal Com",
    "score": 46,
    "earnings_date": "July 14, 2026",
    "days_left": 22,
    "price": 46.63,
    "pe_target": 50.0,
    "pe_upside": 7.2,
    "3d": 56.72,
    "3d_up": 21.6,
    "5d": 63.44,
    "5d_up": 36.0,
    "analysts": 17,
    "sb": 0,
    "buy": 5,
    "hold": 7,
    "sell": 5,
    "mktcap": 0.0,
    "short_int": 2.8,
    "iv": 7.2,
    "sector": "Industrials",
    "sentiment": "Mixed",
    "news": {
      "title": "Here is Why Hedge Funds Fancy Fastenal Co. (FAST)...",
      "url": "https://finance.yahoo.com/markets/stocks/articles/why-hedge-funds-fancy-fastenal-155519156.html"
    },
    "price_change_pct": 1.61
  },
  {
    "rank": 54,
    "ticker": "PKE",
    "company_name": "Park Aerospa",
    "score": 43,
    "earnings_date": "July 14, 2026",
    "days_left": 22,
    "price": 32.85,
    "pe_target": 37.14,
    "pe_upside": 13.1,
    "3d": 45.72,
    "3d_up": 39.2,
    "5d": 54.3,
    "5d_up": 65.3,
    "analysts": 1,
    "sb": 1,
    "buy": 0,
    "hold": 0,
    "sell": 0,
    "mktcap": 0.0,
    "short_int": 5.2,
    "iv": 13.1,
    "sector": "Industrials",
    "sentiment": "",
    "news": {
      "title": "The Zacks Analyst Blog Highlights Alphabet, Broadcom, Johns...",
      "url": "https://finance.yahoo.com/markets/stocks/articles/zacks-analyst-blog-highlights-alphabet-085400144.html"
    },
    "price_change_pct": 0.95
  },
  {
    "rank": 55,
    "ticker": "PAYX",
    "company_name": "Paychex, Inc",
    "score": 43,
    "earnings_date": "June 24, 2026",
    "days_left": 2,
    "price": 97.09,
    "pe_target": 105.79,
    "pe_upside": 9.0,
    "3d": 123.19,
    "3d_up": 26.9,
    "5d": 140.59,
    "5d_up": 44.8,
    "analysts": 18,
    "sb": 0,
    "buy": 2,
    "hold": 12,
    "sell": 4,
    "mktcap": 0.0,
    "short_int": 6.2,
    "iv": 9.0,
    "sector": "Technology",
    "sentiment": "Mixed",
    "news": {
      "title": "What Analyst Projections for Key Metrics Reveal About Pa...",
      "url": "https://finance.yahoo.com/markets/stocks/articles/analyst-projections-key-metrics-reveal-131502588.html"
    },
    "price_change_pct": -1.17
  },
  {
    "rank": 56,
    "ticker": "VRSN",
    "company_name": "VeriSign, In",
    "score": 42,
    "earnings_date": "July 23, 2026",
    "days_left": 31,
    "price": 248.66,
    "pe_target": 262.48,
    "pe_upside": 5.6,
    "3d": 290.12,
    "3d_up": 16.7,
    "5d": 317.76,
    "5d_up": 27.8,
    "analysts": 4,
    "sb": 2,
    "buy": 0,
    "hold": 2,
    "sell": 0,
    "mktcap": 0.0,
    "short_int": 2.4,
    "iv": 5.6,
    "sector": "Technology",
    "sentiment": "Mixed",
    "news": {
      "title": "VeriSign Inc. (VRSN): Renaissance Technologies Ad...",
      "url": "https://finance.yahoo.com/markets/stocks/articles/verisign-inc-vrsn-renaissance-technologies-155404243.html"
    },
    "price_change_pct": -6.04
  },
  {
    "rank": 57,
    "ticker": "SANM",
    "company_name": "Sanmina Corp",
    "score": 40,
    "earnings_date": "July 27, 2026",
    "days_left": 35,
    "price": 252.13,
    "pe_target": 299.43,
    "pe_upside": 18.8,
    "3d": 394.03,
    "3d_up": 56.3,
    "5d": 488.63,
    "5d_up": 93.8,
    "analysts": 4,
    "sb": 0,
    "buy": 1,
    "hold": 3,
    "sell": 0,
    "mktcap": 0.0,
    "short_int": 7.3,
    "iv": 18.8,
    "sector": "Technology",
    "sentiment": "Positive",
    "news": {
      "title": "Sanmina (SANM) Is Up 1.24% in One Week: What You Should Know...",
      "url": "https://finance.yahoo.com/markets/stocks/articles/sanmina-sanm-1-24-one-160002999.html"
    },
    "price_change_pct": 4.41
  },
  {
    "rank": 58,
    "ticker": "RHI",
    "company_name": "Robert Half ",
    "score": 40,
    "earnings_date": "July 22, 2026",
    "days_left": 30,
    "price": 29.4,
    "pe_target": 32.76,
    "pe_upside": 11.4,
    "3d": 39.48,
    "3d_up": 34.3,
    "5d": 46.2,
    "5d_up": 57.1,
    "analysts": 11,
    "sb": 0,
    "buy": 3,
    "hold": 4,
    "sell": 4,
    "mktcap": 0.0,
    "short_int": 28.7,
    "iv": 11.4,
    "sector": "Industrials",
    "sentiment": "Mixed",
    "news": {
      "title": "Is Robert Half (RHI) a Resilient Player in the Industry?...",
      "url": "https://finance.yahoo.com/markets/stocks/articles/robert-half-rhi-resilient-player-121650939.html"
    },
    "price_change_pct": -6.93
  },
  {
    "rank": 59,
    "ticker": "ERIC",
    "company_name": "Telefonaktie",
    "score": 37,
    "earnings_date": "July 14, 2026",
    "days_left": 22,
    "price": 11.65,
    "pe_target": 12.86,
    "pe_upside": 10.4,
    "3d": 15.28,
    "3d_up": 31.1,
    "5d": 17.7,
    "5d_up": 51.9,
    "analysts": 7,
    "sb": 0,
    "buy": 0,
    "hold": 4,
    "sell": 3,
    "mktcap": 0.0,
    "short_int": 1.6,
    "iv": 10.4,
    "sector": "Technology",
    "sentiment": "Positive",
    "news": {
      "title": "European Equities Traded in the US as American Deposi...",
      "url": "https://finance.yahoo.com/markets/world-indices/articles/european-equities-traded-us-american-151044153.html"
    },
    "price_change_pct": 2.37
  },
  {
    "rank": 60,
    "ticker": "WIT",
    "company_name": "Wipro Limite",
    "score": 29,
    "earnings_date": "July 16, 2026",
    "days_left": 24,
    "price": 2.24,
    "pe_target": 2.65,
    "pe_upside": 18.3,
    "3d": 3.47,
    "3d_up": 54.9,
    "5d": 4.29,
    "5d_up": 91.5,
    "analysts": 7,
    "sb": 0,
    "buy": 0,
    "hold": 3,
    "sell": 4,
    "mktcap": 0.0,
    "short_int": 3.0,
    "iv": 18.3,
    "sector": "Technology",
    "sentiment": "Mixed",
    "news": {
      "title": "Wipro Limited (WIT) Gains Due to Share Buyback Program...",
      "url": "https://finance.yahoo.com/markets/stocks/articles/wipro-limited-wit-gains-due-185359971.html"
    },
    "price_change_pct": -6.28
  },
  {
    "rank": 61,
    "ticker": "MAXN",
    "company_name": "Maxeon Solar",
    "score": 0,
    "earnings_date": "June 22, 2026",
    "days_left": 0,
    "price": 0.76,
    "pe_target": 0,
    "pe_upside": 0,
    "3d": 0,
    "3d_up": 0,
    "5d": 0,
    "5d_up": 0,
    "analysts": 0,
    "sb": 0,
    "buy": 0,
    "hold": 0,
    "sell": 0,
    "mktcap": 0.0,
    "short_int": 16.4,
    "iv": 0,
    "sector": "Technology",
    "sentiment": "Negative",
    "news": {
      "title": "Maxeon says it is committed to building massive Albuque...",
      "url": "https://finance.yahoo.com/news/maxeon-says-committed-building-massive-140300285.html"
    },
    "price_change_pct": 0
  },
  {
    "rank": 62,
    "ticker": "INFO",
    "company_name": "Harbor PanAg",
    "score": 0,
    "earnings_date": "July 21, 2026",
    "days_left": 29,
    "price": 27.06,
    "pe_target": 0,
    "pe_upside": 0,
    "3d": 0,
    "3d_up": 0,
    "5d": 0,
    "5d_up": 0,
    "analysts": 0,
    "sb": 0,
    "buy": 0,
    "hold": 0,
    "sell": 0,
    "mktcap": 0,
    "short_int": 0,
    "iv": 0,
    "sector": "Technology",
    "sentiment": "",
    "news": {},
    "price_change_pct": -0.22
  }
]